{"assets/images.json":["assets/images.json"],"assets/login_img/login-1.svg":["assets/login_img/login-1.svg"],"assets/login_img/login-2.svg":["assets/login_img/login-2.svg"],"assets/login_img/login-3.svg":["assets/login_img/login-3.svg"],"assets/login_img/login-3_1.svg":["assets/login_img/login-3_1.svg"],"assets/login_img/login-4.svg":["assets/login_img/login-4.svg"],"assets/login_img/login-5.svg":["assets/login_img/login-5.svg"],"assets/login_img/login-6.svg":["assets/login_img/login-6.svg"],"assets/login_img/login-7.svg":["assets/login_img/login-7.svg"],"assets/login_img/ventax_logo.svg":["assets/login_img/ventax_logo.svg"],"assets/text.json":["assets/text.json"],"packages/cupertino_icons/assets/CupertinoIcons.ttf":["packages/cupertino_icons/assets/CupertinoIcons.ttf"]}